mongo_db_operator/DbClassOperator.py
mongo_db_operator/DbClassOperators.py
mongo_db_operator/MongoDbOperator.py
mongo_db_operator/__init__.py
mongo_db_operator/connect.py
mongo_db_operator-0.1.9.dist-info/LICENSE
mongo_db_operator-0.1.9.dist-info/METADATA
mongo_db_operator-0.1.9.dist-info/WHEEL
mongo_db_operator-0.1.9.dist-info/top_level.txt
mongo_db_operator-0.1.9.dist-info/RECORD
