Metadata-Version: 2.1
Name: mongo-db-operator
Version: 0.1.9
Summary: Seriattrs extension compatible with MongoDb
Home-page: https://github.com/Tesla2000/mongoDataclass
Author: Tesla2000
Author-email: fratajczak124@gmail.com
Project-URL: Homepage, https://github.com/Tesla2000/mongoDataclass
Classifier: Programming Language :: Python :: 3
Classifier: License :: OSI Approved :: MIT License
Classifier: Operating System :: OS Independent
Requires-Python: >=3.11
License-File: LICENSE
Requires-Dist: seriattrs
Requires-Dist: pymongo >=4.6.0
